f04profiling.py
f04profile-0.2.0.dist-info/METADATA
f04profile-0.2.0.dist-info/WHEEL
f04profile-0.2.0.dist-info/entry_points.txt
f04profile-0.2.0.dist-info/top_level.txt
f04profile-0.2.0.dist-info/RECORD
