Metadata-Version: 2.1
Name: f04profile
Version: 0.2.0
Author: Nicolas Cordier
Author-email: nicolas.cordier@numeric-gmbh.ch
Classifier: Development Status :: 4 - Beta
Classifier: Intended Audience :: Developers
Classifier: License :: OSI Approved :: MIT License
Classifier: Natural Language :: English
Classifier: Programming Language :: Python :: 3.8
Classifier: Programming Language :: Python :: 3.9
Requires-Python: >=3.8
Requires-Dist: snakeviz
